pyozk/__init__.py
pyozk/attendance.py
pyozk/base.py
pyozk/const.py
pyozk/database.py
pyozk/exception.py
pyozk/finger.py
pyozk/pubsub.py
pyozk/user.py
pyozk/utility.py
pyozk-0.0.5.dist-info/METADATA
pyozk-0.0.5.dist-info/WHEEL
pyozk-0.0.5.dist-info/licenses/LICENSE
pyozk-0.0.5.dist-info/licenses/LICENSE.txt
pyozk-0.0.5.dist-info/RECORD
