Metadata-Version: 2.1
Name: pyozk
Version: 0.0.5
Summary: A small example package
Project-URL: Homepage, https://github.com/cnguyencong/pyozk
Project-URL: Issues, https://github.com/cnguyencong/pyozk/issues
Author-email: Chinh Nguyen <cnguyencong@owt.swiss>
License-File: LICENSE
License-File: LICENSE.txt
Classifier: License :: OSI Approved :: MIT License
Classifier: Operating System :: OS Independent
Classifier: Programming Language :: Python :: 3
Requires-Python: >=3.8
